application/__init__.py
application/DSE/__init__.py
application/DSE/arguements.py
application/DSE/config_management.py
application/DSE/dse_facade.py
application/DSE/optimization.py
application/DSE/parameter.py
application/DSE/run.py
application/flow/__init__.py
application/flow/run_iEDA_eval.py
application/flow/run_iEDA_flow.py
application/test/__init__.py
database/__init__.py
database/design.py
database/drc.py
database/enum.py
database/large_model.py
database/layout.py
database/summary.py
database/timing.py
engine/__init__.py
engine/base.py
engine/cts.py
engine/db.py
engine/drc.py
engine/floorplan.py
engine/full_flow.py
engine/gds.py
engine/net_opt.py
engine/pdn.py
engine/placement.py
engine/rcx.py
engine/routing.py
engine/sta.py
engine/timing_opt.py
feature/__init__.py
feature/base.py
feature/io.py
feature/lm_graph.py
feature/lm_patch.py
feature/lm_path.py
feature/statis.py
feature/timing.py
flow/__init__.py
flow/flow_db.py
flow/flow_manager.py
flow/run_flow_ieda.py
flow/run_flow_innovus.py
flow/run_flow_openroad.py
tools/__init__.py
tools/fpt/__init__.py
tools/fpt/fpt.py
tools/fpt/main.py
tools/fpt/utility/__init__.py
tools/fpt/utility/report_json.py
tools/fpt/utility/utility.py
tools/fpt/writer/__init__.py
tools/iEDA/__init__.py
utility/__init__.py
utility/folder_permission.py
utility/json_parser.py
utility/jsonl_parser.py
aieda-0.1.0.dist-info/LICENSE
aieda-0.1.0.dist-info/METADATA
aieda-0.1.0.dist-info/WHEEL
aieda-0.1.0.dist-info/entry_points.txt
aieda-0.1.0.dist-info/top_level.txt
aieda-0.1.0.dist-info/RECORD
